package_obfuscator/__init__.py
package_obfuscator/file_obfuscator.py
package_obfuscator/obfuscate_wrapper.py
package_obfuscator/cli/__init__.py
test/__init__.py
test/test_obfuscate_folder.py
test/test_module/__init__.py
test/test_module/hello_world.py
test/test_module/nested/__init__.py
test/test_module/nested/functionality_test.py
package_obfuscator-1.0.2.dist-info/LICENSE
package_obfuscator-1.0.2.dist-info/METADATA
package_obfuscator-1.0.2.dist-info/WHEEL
package_obfuscator-1.0.2.dist-info/entry_points.txt
package_obfuscator-1.0.2.dist-info/top_level.txt
package_obfuscator-1.0.2.dist-info/RECORD
