Metadata-Version: 2.1
Name: package_obfuscator
Version: 1.0.2
Summary: An obfuscator for python packages.
Home-page: https://github.com/bubblegumsoldier/package-obfuscator
Download-URL: https://github.com/bubblegumsoldier/package-obfuscator/tarball/1.0.2
Author: Henry Müssemann
Author-email: hm@hm-dev-consulting.de
License: MIT
Keywords: obfuscator
Classifier: Development Status :: 3 - Alpha
Classifier: Intended Audience :: Developers
Classifier: Topic :: Software Development :: Build Tools
Classifier: License :: OSI Approved :: MIT License
Classifier: Programming Language :: Python :: 3.6
Classifier: Programming Language :: Python :: 3.7
Classifier: Programming Language :: Python :: 3.8
Classifier: Programming Language :: Python :: 3.9
Classifier: Programming Language :: Python :: 3.10
Classifier: Programming Language :: Python :: 3.11
Classifier: Programming Language :: Python :: 3.12
License-File: LICENSE
